{"copyright":"Copyright © 2008 DESI Telephone Labels, Inc.","group":"Teledex iPhone","typeCode":"TISIP25","description":"iPhone SIP 2-Line 5SPD","landscape":false,"width":4614,"height":12139,"origins":[[860,2180],[6454,2180]],"objects":{"4496":{"kind":"staticText","color":"#000","position":[100,100,1100,350],"defaultText":"Comments:"},"4796":{"kind":"text","printable":true,"editable":true,"color":"#c0ffff","position":[100,350,4514,850],"defaultText":""},"5096":{"kind":"text","printable":true,"editable":true,"color":"#fff","position":[638,1050,4031,1669],"defaultText":""},"5462":{"kind":"text","printable":true,"editable":true,"color":"#fff","position":[638,1685,2334,1837],"defaultText":"{\\rtf1\\ansi{\\fonttbl{\\f0\\ftnil Arial;}}{\\colortbl;}\\f0\\cf0\\fs14\\ql }"},"5828":{"kind":"text","printable":true,"editable":true,"color":"#fff","position":[2335,1685,4031,1837],"defaultText":"{\\rtf1\\ansi{\\fonttbl{\\f0\\ftnil Arial;}}{\\colortbl;}\\f0\\cf0\\fs14\\qr }"},"6194":{"kind":"text","printable":true,"editable":true,"color":"#fff","position":[638,1847,2334,1999],"defaultText":"{\\rtf1\\ansi{\\fonttbl{\\f0\\ftnil Arial;}}{\\colortbl;}\\f0\\cf0\\fs14\\ql }"},"6560":{"kind":"text","printable":true,"editable":true,"color":"#fff","position":[2335,1847,4031,1999],"defaultText":"{\\rtf1\\ansi{\\fonttbl{\\f0\\ftnil Arial;}}{\\colortbl;}\\f0\\cf0\\fs14\\qr }"},"6926":{"kind":"text","printable":true,"editable":true,"color":"#fff","position":[638,2009,2334,2161],"defaultText":"{\\rtf1\\ansi{\\fonttbl{\\f0\\ftnil Arial;}}{\\colortbl;}\\f0\\cf0\\fs14\\ql }"},"7292":{"kind":"text","printable":true,"editable":true,"color":"#fff","position":[2335,2009,4031,2161],"defaultText":"{\\rtf1\\ansi{\\fonttbl{\\f0\\ftnil Arial;}}{\\colortbl;}\\f0\\cf0\\fs14\\qr }"},"7658":{"kind":"text","printable":true,"editable":true,"color":"#fff","position":[638,2171,2334,2323],"defaultText":"{\\rtf1\\ansi{\\fonttbl{\\f0\\ftnil Arial;}}{\\colortbl;}\\f0\\cf0\\fs14\\ql }"},"8024":{"kind":"text","printable":true,"editable":true,"color":"#fff","position":[2335,2171,4031,2323],"defaultText":"{\\rtf1\\ansi{\\fonttbl{\\f0\\ftnil Arial;}}{\\colortbl;}\\f0\\cf0\\fs14\\qr }"},"8390":{"kind":"text","printable":true,"editable":true,"color":"#fff","position":[638,2333,2334,2485],"defaultText":"{\\rtf1\\ansi{\\fonttbl{\\f0\\ftnil Arial;}}{\\colortbl;}\\f0\\cf0\\fs14\\ql }"},"8756":{"kind":"text","printable":true,"editable":true,"color":"#fff","position":[2335,2333,4031,2485],"defaultText":"{\\rtf1\\ansi{\\fonttbl{\\f0\\ftnil Arial;}}{\\colortbl;}\\f0\\cf0\\fs14\\qr }"},"9122":{"kind":"text","printable":true,"editable":true,"color":"#fff","position":[638,2495,2334,2647],"defaultText":"{\\rtf1\\ansi{\\fonttbl{\\f0\\ftnil Arial;}}{\\colortbl;}\\f0\\cf0\\fs14\\ql }"},"9488":{"kind":"text","printable":true,"editable":true,"color":"#fff","position":[2335,2495,4031,2647],"defaultText":"{\\rtf1\\ansi{\\fonttbl{\\f0\\ftnil Arial;}}{\\colortbl;}\\f0\\cf0\\fs14\\qr }"},"9854":{"kind":"text","printable":true,"editable":true,"color":"#fff","position":[638,2657,2334,2809],"defaultText":"{\\rtf1\\ansi{\\fonttbl{\\f0\\ftnil Arial;}}{\\colortbl;}\\f0\\cf0\\fs14\\ql }"},"10220":{"kind":"text","printable":true,"editable":true,"color":"#fff","position":[2335,2657,4031,2809],"defaultText":"{\\rtf1\\ansi{\\fonttbl{\\f0\\ftnil Arial;}}{\\colortbl;}\\f0\\cf0\\fs14\\qr }"},"10586":{"kind":"text","printable":true,"editable":true,"color":"#fff","position":[638,2819,2334,2971],"defaultText":"{\\rtf1\\ansi{\\fonttbl{\\f0\\ftnil Arial;}}{\\colortbl;}\\f0\\cf0\\fs14\\ql }"},"10952":{"kind":"text","printable":true,"editable":true,"color":"#fff","position":[2335,2819,4031,2971],"defaultText":"{\\rtf1\\ansi{\\fonttbl{\\f0\\ftnil Arial;}}{\\colortbl;}\\f0\\cf0\\fs14\\qr }"},"11318":{"kind":"text","printable":true,"editable":true,"color":"#fff","position":[638,2981,2334,3133],"defaultText":"{\\rtf1\\ansi{\\fonttbl{\\f0\\ftnil Arial;}}{\\colortbl;}\\f0\\cf0\\fs14\\ql }"},"11684":{"kind":"text","printable":true,"editable":true,"color":"#fff","position":[2335,2981,4031,3133],"defaultText":"{\\rtf1\\ansi{\\fonttbl{\\f0\\ftnil Arial;}}{\\colortbl;}\\f0\\cf0\\fs14\\qr }"},"12050":{"kind":"text","printable":true,"editable":true,"color":"#fff","position":[638,3143,2334,3295],"defaultText":"{\\rtf1\\ansi{\\fonttbl{\\f0\\ftnil Arial;}}{\\colortbl;}\\f0\\cf0\\fs14\\ql }"},"12416":{"kind":"text","printable":true,"editable":true,"color":"#fff","position":[2335,3143,4031,3295],"defaultText":"{\\rtf1\\ansi{\\fonttbl{\\f0\\ftnil Arial;}}{\\colortbl;}\\f0\\cf0\\fs14\\qr }"},"12782":{"kind":"text","printable":true,"editable":true,"color":"#fff","position":[638,3305,2334,3457],"defaultText":"{\\rtf1\\ansi{\\fonttbl{\\f0\\ftnil Arial;}}{\\colortbl;}\\f0\\cf0\\fs14\\ql }"},"13148":{"kind":"text","printable":true,"editable":true,"color":"#fff","position":[2335,3305,4031,3457],"defaultText":"{\\rtf1\\ansi{\\fonttbl{\\f0\\ftnil Arial;}}{\\colortbl;}\\f0\\cf0\\fs14\\qr }"},"13514":{"kind":"text","printable":true,"editable":true,"color":"#fff","position":[638,3467,2334,3619],"defaultText":"{\\rtf1\\ansi{\\fonttbl{\\f0\\ftnil Arial;}}{\\colortbl;}\\f0\\cf0\\fs14\\ql }"},"13880":{"kind":"text","printable":true,"editable":true,"color":"#fff","position":[2335,3467,4031,3619],"defaultText":"{\\rtf1\\ansi{\\fonttbl{\\f0\\ftnil Arial;}}{\\colortbl;}\\f0\\cf0\\fs14\\qr }"},"14246":{"kind":"text","printable":true,"editable":true,"color":"#fff","position":[638,3629,2334,3781],"defaultText":"{\\rtf1\\ansi{\\fonttbl{\\f0\\ftnil Arial;}}{\\colortbl;}\\f0\\cf0\\fs14\\ql }"},"14612":{"kind":"text","printable":true,"editable":true,"color":"#fff","position":[2335,3629,4031,3781],"defaultText":"{\\rtf1\\ansi{\\fonttbl{\\f0\\ftnil Arial;}}{\\colortbl;}\\f0\\cf0\\fs14\\qr }"},"14978":{"kind":"text","printable":true,"editable":true,"color":"#fff","position":[638,3791,2334,3943],"defaultText":"{\\rtf1\\ansi{\\fonttbl{\\f0\\ftnil Arial;}}{\\colortbl;}\\f0\\cf0\\fs14\\ql }"},"15344":{"kind":"text","printable":true,"editable":true,"color":"#fff","position":[2335,3791,4031,3943],"defaultText":"{\\rtf1\\ansi{\\fonttbl{\\f0\\ftnil Arial;}}{\\colortbl;}\\f0\\cf0\\fs14\\qr }"},"20096":{"kind":"text","printable":true,"editable":true,"color":"#fff","position":[638,3953,4031,4429],"defaultText":""},"21096":{"kind":"text","printable":true,"editable":true,"color":"#fff","position":[4084,1950,4224,3250],"defaultText":"{\\rtf1\\ansi{\\fonttbl{\\f0\\ftnil Arial;}}{\\colortbl;}\\f0\\cf0\\fs12\\qc D\\par A\\par T\\par A}"},"37096":{"kind":"text","printable":true,"editable":true,"color":"#fff","position":[538,4572,1235,4955],"defaultText":"{\\rtf1\\ansi{\\fonttbl{\\f0\\ftnil DESI Pictograms;}}{\\colortbl;}\\f0\\cf0\\fs50\\qc }"},"38096":{"kind":"text","printable":true,"editable":true,"color":"#fff","position":[538,5398,1235,5550],"defaultText":"{\\rtf1\\ansi{\\fonttbl{\\f0\\ftnil Arial;}}{\\colortbl;}\\f0\\cf0\\fs14\\qc }"},"39096":{"kind":"text","printable":true,"editable":true,"color":"#fff","position":[538,5550,1235,5702],"defaultText":"{\\rtf1\\ansi{\\fonttbl{\\f0\\ftnil Arial;}}{\\colortbl;}\\f0\\cf0\\fs14\\qc }"},"40096":{"kind":"text","printable":true,"editable":true,"color":"#fff","position":[1262,4572,1959,4955],"defaultText":"{\\rtf1\\ansi{\\fonttbl{\\f0\\ftnil DESI Pictograms;}}{\\colortbl;}\\f0\\cf0\\fs50\\qc }"},"41096":{"kind":"text","printable":true,"editable":true,"color":"#fff","position":[1262,5398,1959,5550],"defaultText":"{\\rtf1\\ansi{\\fonttbl{\\f0\\ftnil Arial;}}{\\colortbl;}\\f0\\cf0\\fs14\\qc }"},"42096":{"kind":"text","printable":true,"editable":true,"color":"#fff","position":[1262,5550,1959,5702],"defaultText":"{\\rtf1\\ansi{\\fonttbl{\\f0\\ftnil Arial;}}{\\colortbl;}\\f0\\cf0\\fs14\\qc }"},"43096":{"kind":"text","printable":true,"editable":true,"color":"#fff","position":[1986,4572,2683,4955],"defaultText":"{\\rtf1\\ansi{\\fonttbl{\\f0\\ftnil DESI Pictograms;}}{\\colortbl;}\\f0\\cf0\\fs50\\qc }"},"44096":{"kind":"text","printable":true,"editable":true,"color":"#fff","position":[1986,5398,2683,5550],"defaultText":"{\\rtf1\\ansi{\\fonttbl{\\f0\\ftnil Arial;}}{\\colortbl;}\\f0\\cf0\\fs14\\qc }"},"45096":{"kind":"text","printable":true,"editable":true,"color":"#fff","position":[1986,5550,2683,5702],"defaultText":"{\\rtf1\\ansi{\\fonttbl{\\f0\\ftnil Arial;}}{\\colortbl;}\\f0\\cf0\\fs14\\qc }"},"46096":{"kind":"text","printable":true,"editable":true,"color":"#fff","position":[2710,4572,3407,4955],"defaultText":"{\\rtf1\\ansi{\\fonttbl{\\f0\\ftnil DESI Pictograms;}}{\\colortbl;}\\f0\\cf0\\fs50\\qc }"},"47096":{"kind":"text","printable":true,"editable":true,"color":"#fff","position":[2710,5398,3407,5550],"defaultText":"{\\rtf1\\ansi{\\fonttbl{\\f0\\ftnil Arial;}}{\\colortbl;}\\f0\\cf0\\fs14\\qc }"},"48096":{"kind":"text","printable":true,"editable":true,"color":"#fff","position":[2710,5550,3407,5702],"defaultText":"{\\rtf1\\ansi{\\fonttbl{\\f0\\ftnil Arial;}}{\\colortbl;}\\f0\\cf0\\fs14\\qc }"},"49096":{"kind":"text","printable":true,"editable":true,"color":"#fff","position":[3434,4572,4131,4955],"defaultText":"{\\rtf1\\ansi{\\fonttbl{\\f0\\ftnil DESI Pictograms;}}{\\colortbl;}\\f0\\cf0\\fs50\\qc }"},"50096":{"kind":"text","printable":true,"editable":true,"color":"#fff","position":[3434,5398,4131,5550],"defaultText":"{\\rtf1\\ansi{\\fonttbl{\\f0\\ftnil Arial;}}{\\colortbl;}\\f0\\cf0\\fs14\\qc }"},"51096":{"kind":"text","printable":true,"editable":true,"color":"#fff","position":[3434,5550,4131,5702],"defaultText":"{\\rtf1\\ansi{\\fonttbl{\\f0\\ftnil Arial;}}{\\colortbl;}\\f0\\cf0\\fs14\\qc }"},"52096":{"kind":"text","printable":true,"editable":true,"color":"#fff","position":[638,5752,4031,6304],"defaultText":""},"53096":{"kind":"text","printable":true,"editable":true,"color":"#fff","position":[638,6320,4031,6872],"defaultText":""},"54096":{"kind":"text","printable":true,"editable":true,"color":"#fff","position":[296,9358,969,9561],"defaultText":"{\\rtf1\\ansi{\\fonttbl{\\f0\\ftnil Arial;}}{\\colortbl;}\\f0\\cf0\\fs14\\qc VOLUME}"},"55096":{"kind":"text","printable":true,"editable":true,"color":"#fff","position":[536,10874,1238,11077],"defaultText":"{\\rtf1\\ansi{\\fonttbl{\\f0\\ftnil Arial;}}{\\colortbl;}\\f0\\cf0\\fs14\\qc SPEAKER}"},"56096":{"kind":"text","printable":true,"editable":true,"color":"#fff","position":[1260,10874,1962,11077],"defaultText":"{\\rtf1\\ansi{\\fonttbl{\\f0\\ftnil Arial;}}{\\colortbl;}\\f0\\cf0\\fs14\\qc FLASH}"},"57096":{"kind":"text","printable":true,"editable":true,"color":"#fff","position":[1984,10874,2686,11077],"defaultText":"{\\rtf1\\ansi{\\fonttbl{\\f0\\ftnil Arial;}}{\\colortbl;}\\f0\\cf0\\fs14\\qc MUTE}"},"58096":{"kind":"text","printable":true,"editable":true,"color":"#fff","position":[2708,10874,3410,11077],"defaultText":"{\\rtf1\\ansi{\\fonttbl{\\f0\\ftnil Arial;}}{\\colortbl;}\\f0\\cf0\\fs14\\qc REDIAL}"},"59096":{"kind":"text","printable":true,"editable":true,"color":"#fff","position":[3432,10874,4134,11077],"defaultText":"{\\rtf1\\ansi{\\fonttbl{\\f0\\ftnil Arial;}}{\\colortbl;}\\f0\\cf0\\fs14\\qc HOLD}"},"60096":{"kind":"text","printable":true,"editable":true,"color":"#fff","position":[536,11784,1238,11987],"defaultText":"{\\rtf1\\ansi{\\fonttbl{\\f0\\ftnil Arial;}}{\\colortbl;}\\f0\\cf0\\fs14\\qc LINE}"},"61096":{"kind":"text","printable":true,"editable":true,"color":"#fff","position":[1260,11784,1962,11987],"defaultText":"{\\rtf1\\ansi{\\fonttbl{\\f0\\ftnil Arial;}}{\\colortbl;}\\f0\\cf0\\fs14\\qc LINE 2}"},"62096":{"kind":"text","printable":true,"editable":true,"color":"#fff","position":[1984,11784,2686,11987],"defaultText":"{\\rtf1\\ansi{\\fonttbl{\\f0\\ftnil Arial;}}{\\colortbl;}\\f0\\cf0\\fs14\\qc CONF}"},"63096":{"kind":"text","printable":true,"editable":true,"color":"#fff","position":[2842,11604,4000,11756],"defaultText":"{\\rtf1\\ansi{\\fonttbl{\\f0\\ftnil Arial;}}{\\colortbl;}\\f0\\cf0\\fs14\\qc MESSAGE}"},"69096":{"kind":"ellipse","outlineOnly":true,"dim":true,"color":"#808080","position":[603,4985,1170,5368],"defaultText":""},"70096":{"kind":"ellipse","outlineOnly":true,"dim":true,"color":"#808080","position":[1327,4985,1894,5368],"defaultText":""},"71096":{"kind":"ellipse","outlineOnly":true,"dim":true,"color":"#808080","position":[2051,4985,2618,5368],"defaultText":""},"72096":{"kind":"ellipse","outlineOnly":true,"dim":true,"color":"#808080","position":[2775,4985,3342,5368],"defaultText":""},"73096":{"kind":"ellipse","outlineOnly":true,"dim":true,"color":"#808080","position":[3499,4985,4066,5368],"defaultText":""},"74096":{"kind":"ellipse","outlineOnly":true,"dim":true,"color":"#808080","position":[1052,6939,1926,7528],"defaultText":""},"75096":{"kind":"ellipse","outlineOnly":true,"dim":true,"color":"#808080","position":[2157,6939,3031,7528],"defaultText":""},"76096":{"kind":"ellipse","outlineOnly":true,"dim":true,"color":"#808080","position":[3262,6939,4136,7528],"defaultText":""},"77096":{"kind":"ellipse","outlineOnly":true,"dim":true,"color":"#808080","position":[1052,7769,1926,8358],"defaultText":""},"78096":{"kind":"ellipse","outlineOnly":true,"dim":true,"color":"#808080","position":[2157,7769,3031,8358],"defaultText":""},"79096":{"kind":"ellipse","outlineOnly":true,"dim":true,"color":"#808080","position":[3262,7769,4136,8358],"defaultText":""},"80096":{"kind":"ellipse","outlineOnly":true,"dim":true,"color":"#808080","position":[1052,8599,1926,9188],"defaultText":""},"81096":{"kind":"ellipse","outlineOnly":true,"dim":true,"color":"#808080","position":[2157,8599,3031,9188],"defaultText":""},"82096":{"kind":"ellipse","outlineOnly":true,"dim":true,"color":"#808080","position":[3262,8599,4136,9188],"defaultText":""},"83096":{"kind":"ellipse","outlineOnly":true,"dim":true,"color":"#808080","position":[1052,9429,1926,10018],"defaultText":""},"84096":{"kind":"ellipse","outlineOnly":true,"dim":true,"color":"#808080","position":[2157,9429,3031,10018],"defaultText":""},"85096":{"kind":"ellipse","outlineOnly":true,"dim":true,"color":"#808080","position":[3262,9429,4136,10018],"defaultText":""},"86096":{"kind":"roundedRect","outlineOnly":true,"dim":true,"color":"#808080","position":[401,7731,804,8467],"defaultText":""},"87096":{"kind":"roundedRect","outlineOnly":true,"dim":true,"color":"#808080","position":[401,8592,804,9328],"defaultText":""},"88096":{"kind":"ellipse","outlineOnly":true,"dim":true,"color":"#808080","position":[603,10476,1170,10859],"defaultText":""},"89096":{"kind":"ellipse","outlineOnly":true,"dim":true,"color":"#808080","position":[1327,10476,1894,10859],"defaultText":""},"90096":{"kind":"ellipse","outlineOnly":true,"dim":true,"color":"#808080","position":[2051,10476,2618,10859],"defaultText":""},"91096":{"kind":"ellipse","outlineOnly":true,"dim":true,"color":"#808080","position":[2775,10476,3342,10859],"defaultText":""},"92096":{"kind":"ellipse","outlineOnly":true,"dim":true,"color":"#808080","position":[3499,10476,4066,10859],"defaultText":""},"93096":{"kind":"ellipse","outlineOnly":true,"dim":true,"color":"#808080","position":[603,11115,1170,11498],"defaultText":""},"94096":{"kind":"ellipse","outlineOnly":true,"dim":true,"color":"#808080","position":[1327,11115,1894,11498],"defaultText":""},"95096":{"kind":"ellipse","outlineOnly":true,"dim":true,"color":"#808080","position":[2051,11115,2618,11498],"defaultText":""},"96096":{"kind":"ellipse","outlineOnly":true,"dim":true,"color":"#808080","position":[2902,11100,3940,11574],"defaultText":""},"97096":{"kind":"ellipse","outlineOnly":true,"dim":true,"color":"#808080","position":[807,10240,967,10400],"defaultText":""},"98096":{"kind":"ellipse","outlineOnly":true,"dim":true,"color":"#808080","position":[2255,10240,2415,10400],"defaultText":""},"100096":{"kind":"ellipse","outlineOnly":true,"dim":true,"color":"#808080","position":[807,11609,967,11769],"defaultText":""},"100596":{"kind":"ellipse","outlineOnly":true,"dim":true,"color":"#808080","position":[1531,11609,1691,11769],"defaultText":""},"101096":{"kind":"ellipse","outlineOnly":true,"dim":true,"color":"#808080","position":[2255,11609,2415,11769],"defaultText":""},"103096":{"kind":"dottedLine","color":"#000","position":[100,950,4514,12039],"defaultText":""}}}
