{"copyright":"Copyright © 2009 DESI Telephone Labels, Inc.","group":"Vertical Triad","typeCode":"VTR24EN","description":"24 Enhanced Exec","landscape":false,"width":9150,"height":5568,"origins":[[1328,2267],[1328,8459]],"objects":{"5096":{"kind":"text","printable":true,"editable":true,"color":"#fff","position":[589,120,3051,794],"defaultText":""},"6096":{"kind":"ellipse","outlineOnly":true,"color":"#000","position":[532,1519,757,1744],"defaultText":""},"7096":{"kind":"ellipse","outlineOnly":true,"color":"#000","position":[2908,1519,3133,1744],"defaultText":""},"8096":{"kind":"text","printable":true,"editable":true,"color":"#fff","position":[155,1992,1805,2217],"defaultText":"{\\rtf1\\ansi{\\fonttbl{\\f0\\ftnil Arial;}}{\\colortbl\\red0green0blue0;}\\f0\\cf0\\fs16\\b\\qc NUMBER}"},"9096":{"kind":"text","printable":true,"editable":true,"color":"#fff","position":[1856,1992,3506,2217],"defaultText":"{\\rtf1\\ansi{\\fonttbl{\\f0\\ftnil Arial;}}{\\colortbl\\red0green0blue0;}\\f0\\cf0\\fs16\\b\\qc NAME}"},"10096":{"kind":"text","printable":true,"editable":true,"color":"#fff","position":[155,2378,1805,2603],"defaultText":"{\\rtf1\\ansi{\\fonttbl{\\f0\\ftnil Arial;}}{\\colortbl\\red0green0blue0;}\\f0\\cf0\\fs16\\qc }"},"11096":{"kind":"text","printable":true,"editable":true,"color":"#fff","position":[1856,2378,3506,2603],"defaultText":"{\\rtf1\\ansi{\\fonttbl{\\f0\\ftnil Arial;}}{\\colortbl\\red0green0blue0;}\\f0\\cf0\\fs16\\qc }"},"12096":{"kind":"text","printable":true,"editable":true,"color":"#fff","position":[155,2678,1805,2903],"defaultText":"{\\rtf1\\ansi{\\fonttbl{\\f0\\ftnil Arial;}}{\\colortbl\\red0green0blue0;}\\f0\\cf0\\fs16\\qc }"},"13096":{"kind":"text","printable":true,"editable":true,"color":"#fff","position":[1856,2678,3506,2903],"defaultText":"{\\rtf1\\ansi{\\fonttbl{\\f0\\ftnil Arial;}}{\\colortbl\\red0green0blue0;}\\f0\\cf0\\fs16\\qc }"},"14096":{"kind":"text","printable":true,"editable":true,"color":"#fff","position":[155,2978,1805,3203],"defaultText":"{\\rtf1\\ansi{\\fonttbl{\\f0\\ftnil Arial;}}{\\colortbl\\red0green0blue0;}\\f0\\cf0\\fs16\\qc }"},"15096":{"kind":"text","printable":true,"editable":true,"color":"#fff","position":[1856,2978,3506,3203],"defaultText":"{\\rtf1\\ansi{\\fonttbl{\\f0\\ftnil Arial;}}{\\colortbl\\red0green0blue0;}\\f0\\cf0\\fs16\\qc }"},"16096":{"kind":"text","printable":true,"editable":true,"color":"#fff","position":[155,3278,1805,3503],"defaultText":"{\\rtf1\\ansi{\\fonttbl{\\f0\\ftnil Arial;}}{\\colortbl\\red0green0blue0;}\\f0\\cf0\\fs16\\qc }"},"17096":{"kind":"text","printable":true,"editable":true,"color":"#fff","position":[1856,3278,3506,3503],"defaultText":"{\\rtf1\\ansi{\\fonttbl{\\f0\\ftnil Arial;}}{\\colortbl\\red0green0blue0;}\\f0\\cf0\\fs16\\qc }"},"18096":{"kind":"text","printable":true,"editable":true,"color":"#fff","position":[155,3578,1805,3803],"defaultText":"{\\rtf1\\ansi{\\fonttbl{\\f0\\ftnil Arial;}}{\\colortbl\\red0green0blue0;}\\f0\\cf0\\fs16\\qc }"},"19096":{"kind":"text","printable":true,"editable":true,"color":"#fff","position":[1856,3578,3506,3803],"defaultText":"{\\rtf1\\ansi{\\fonttbl{\\f0\\ftnil Arial;}}{\\colortbl\\red0green0blue0;}\\f0\\cf0\\fs16\\qc }"},"20096":{"kind":"text","printable":true,"editable":true,"color":"#fff","position":[155,3878,1805,4103],"defaultText":"{\\rtf1\\ansi{\\fonttbl{\\f0\\ftnil Arial;}}{\\colortbl\\red0green0blue0;}\\f0\\cf0\\fs16\\qc }"},"21096":{"kind":"text","printable":true,"editable":true,"color":"#fff","position":[1856,3878,3506,4103],"defaultText":"{\\rtf1\\ansi{\\fonttbl{\\f0\\ftnil Arial;}}{\\colortbl\\red0green0blue0;}\\f0\\cf0\\fs16\\qc }"},"22096":{"kind":"text","printable":true,"editable":true,"color":"#fff","position":[155,4178,1805,4403],"defaultText":"{\\rtf1\\ansi{\\fonttbl{\\f0\\ftnil Arial;}}{\\colortbl\\red0green0blue0;}\\f0\\cf0\\fs16\\qc }"},"23096":{"kind":"text","printable":true,"editable":true,"color":"#fff","position":[1856,4178,3506,4403],"defaultText":"{\\rtf1\\ansi{\\fonttbl{\\f0\\ftnil Arial;}}{\\colortbl\\red0green0blue0;}\\f0\\cf0\\fs16\\qc }"},"24096":{"kind":"text","printable":true,"editable":true,"color":"#fff","position":[155,4478,1805,4703],"defaultText":"{\\rtf1\\ansi{\\fonttbl{\\f0\\ftnil Arial;}}{\\colortbl\\red0green0blue0;}\\f0\\cf0\\fs16\\qc }"},"25096":{"kind":"text","printable":true,"editable":true,"color":"#fff","position":[1856,4478,3506,4703],"defaultText":"{\\rtf1\\ansi{\\fonttbl{\\f0\\ftnil Arial;}}{\\colortbl\\red0green0blue0;}\\f0\\cf0\\fs16\\qc }"},"26096":{"kind":"text","printable":true,"editable":true,"color":"#fff","position":[155,4778,1805,5003],"defaultText":"{\\rtf1\\ansi{\\fonttbl{\\f0\\ftnil Arial;}}{\\colortbl\\red0green0blue0;}\\f0\\cf0\\fs16\\qc }"},"27096":{"kind":"text","printable":true,"editable":true,"color":"#fff","position":[1856,4778,3506,5003],"defaultText":"{\\rtf1\\ansi{\\fonttbl{\\f0\\ftnil Arial;}}{\\colortbl\\red0green0blue0;}\\f0\\cf0\\fs16\\qc }"},"28096":{"kind":"dottedLine","color":"#000","position":[100,1294,3601,5142],"defaultText":""},"29096":{"kind":"text","printable":true,"editable":true,"color":"#fff","position":[4385,193,5420,563],"defaultText":""},"30096":{"kind":"text","printable":true,"editable":true,"color":"#fff","position":[5554,193,6589,563],"defaultText":""},"31096":{"kind":"text","printable":true,"editable":true,"color":"#fff","position":[6724,193,7759,563],"defaultText":""},"32096":{"kind":"text","printable":true,"editable":true,"color":"#fff","position":[7893,193,8928,563],"defaultText":""},"33096":{"kind":"text","printable":true,"editable":true,"color":"#fff","position":[4385,895,5420,1265],"defaultText":""},"34096":{"kind":"text","printable":true,"editable":true,"color":"#fff","position":[5554,895,6589,1265],"defaultText":""},"35096":{"kind":"text","printable":true,"editable":true,"color":"#fff","position":[6724,895,7759,1265],"defaultText":""},"36096":{"kind":"text","printable":true,"editable":true,"color":"#fff","position":[7893,895,8928,1265],"defaultText":""},"37096":{"kind":"text","printable":true,"editable":true,"color":"#fff","position":[4385,1597,5420,1967],"defaultText":""},"38096":{"kind":"text","printable":true,"editable":true,"color":"#fff","position":[5554,1597,6589,1967],"defaultText":""},"39096":{"kind":"text","printable":true,"editable":true,"color":"#fff","position":[6724,1597,7759,1967],"defaultText":""},"40096":{"kind":"text","printable":true,"editable":true,"color":"#fff","position":[7893,1597,8928,1967],"defaultText":""},"41096":{"kind":"text","printable":true,"editable":true,"color":"#fff","position":[4385,2299,5420,2669],"defaultText":""},"42096":{"kind":"text","printable":true,"editable":true,"color":"#fff","position":[5554,2299,6589,2669],"defaultText":""},"43096":{"kind":"text","printable":true,"editable":true,"color":"#fff","position":[6724,2299,7759,2669],"defaultText":""},"44096":{"kind":"text","printable":true,"editable":true,"color":"#fff","position":[7893,2299,8928,2669],"defaultText":""},"45096":{"kind":"text","printable":true,"editable":true,"color":"#fff","position":[4385,3002,5420,3372],"defaultText":""},"46096":{"kind":"text","printable":true,"editable":true,"color":"#fff","position":[5554,3002,6589,3372],"defaultText":""},"47096":{"kind":"text","printable":true,"editable":true,"color":"#fff","position":[6724,3002,7759,3372],"defaultText":""},"48096":{"kind":"text","printable":true,"editable":true,"color":"#fff","position":[7893,3002,8928,3372],"defaultText":""},"49096":{"kind":"text","printable":true,"editable":true,"color":"#fff","position":[4385,3704,5420,4074],"defaultText":""},"50096":{"kind":"text","printable":true,"editable":true,"color":"#fff","position":[5554,3704,6589,4074],"defaultText":""},"51096":{"kind":"text","printable":true,"editable":true,"color":"#fff","position":[6724,3704,7759,4074],"defaultText":""},"52096":{"kind":"text","printable":true,"editable":true,"color":"#fff","position":[7893,3704,8928,4074],"defaultText":""},"53096":{"kind":"ellipse","outlineOnly":true,"color":"#000","position":[4485,636,4674,825],"defaultText":""},"54096":{"kind":"dottedLine","color":"#000","position":[4758,613,5394,848],"defaultText":""},"55096":{"kind":"ellipse","outlineOnly":true,"color":"#000","position":[5654,636,5843,825],"defaultText":""},"56096":{"kind":"dottedLine","color":"#000","position":[5927,613,6563,848],"defaultText":""},"57096":{"kind":"ellipse","outlineOnly":true,"color":"#000","position":[6824,636,7013,825],"defaultText":""},"58096":{"kind":"dottedLine","color":"#000","position":[7097,613,7733,848],"defaultText":""},"59096":{"kind":"ellipse","outlineOnly":true,"color":"#000","position":[7993,636,8182,825],"defaultText":""},"60096":{"kind":"dottedLine","color":"#000","position":[8266,613,8902,848],"defaultText":""},"61096":{"kind":"ellipse","outlineOnly":true,"color":"#000","position":[4485,1338,4674,1527],"defaultText":""},"62096":{"kind":"dottedLine","color":"#000","position":[4758,1315,5394,1550],"defaultText":""},"63096":{"kind":"ellipse","outlineOnly":true,"color":"#000","position":[5654,1338,5843,1527],"defaultText":""},"64096":{"kind":"dottedLine","color":"#000","position":[5927,1315,6563,1550],"defaultText":""},"65096":{"kind":"ellipse","outlineOnly":true,"color":"#000","position":[6824,1338,7013,1527],"defaultText":""},"66096":{"kind":"dottedLine","color":"#000","position":[7097,1315,7733,1550],"defaultText":""},"67096":{"kind":"ellipse","outlineOnly":true,"color":"#000","position":[7993,1338,8182,1527],"defaultText":""},"68096":{"kind":"dottedLine","color":"#000","position":[8266,1315,8902,1550],"defaultText":""},"69096":{"kind":"ellipse","outlineOnly":true,"color":"#000","position":[4485,2040,4674,2229],"defaultText":""},"70096":{"kind":"dottedLine","color":"#000","position":[4758,2017,5394,2252],"defaultText":""},"71096":{"kind":"ellipse","outlineOnly":true,"color":"#000","position":[5654,2040,5843,2229],"defaultText":""},"72096":{"kind":"dottedLine","color":"#000","position":[5927,2017,6563,2252],"defaultText":""},"73096":{"kind":"ellipse","outlineOnly":true,"color":"#000","position":[6824,2040,7013,2229],"defaultText":""},"74096":{"kind":"dottedLine","color":"#000","position":[7097,2017,7733,2252],"defaultText":""},"75096":{"kind":"ellipse","outlineOnly":true,"color":"#000","position":[7993,2040,8182,2229],"defaultText":""},"76096":{"kind":"dottedLine","color":"#000","position":[8266,2017,8902,2252],"defaultText":""},"77096":{"kind":"ellipse","outlineOnly":true,"color":"#000","position":[4485,2742,4674,2931],"defaultText":""},"78096":{"kind":"dottedLine","color":"#000","position":[4758,2719,5394,2954],"defaultText":""},"79096":{"kind":"ellipse","outlineOnly":true,"color":"#000","position":[5654,2742,5843,2931],"defaultText":""},"80096":{"kind":"dottedLine","color":"#000","position":[5927,2719,6563,2954],"defaultText":""},"81096":{"kind":"ellipse","outlineOnly":true,"color":"#000","position":[6824,2742,7013,2931],"defaultText":""},"82096":{"kind":"dottedLine","color":"#000","position":[7097,2719,7733,2954],"defaultText":""},"83096":{"kind":"ellipse","outlineOnly":true,"color":"#000","position":[7993,2742,8182,2931],"defaultText":""},"84096":{"kind":"dottedLine","color":"#000","position":[8266,2719,8902,2954],"defaultText":""},"85096":{"kind":"ellipse","outlineOnly":true,"color":"#000","position":[4485,3445,4674,3634],"defaultText":""},"86096":{"kind":"dottedLine","color":"#000","position":[4758,3422,5394,3657],"defaultText":""},"87096":{"kind":"ellipse","outlineOnly":true,"color":"#000","position":[5654,3445,5843,3634],"defaultText":""},"88096":{"kind":"dottedLine","color":"#000","position":[5927,3422,6563,3657],"defaultText":""},"89096":{"kind":"ellipse","outlineOnly":true,"color":"#000","position":[6824,3445,7013,3634],"defaultText":""},"90096":{"kind":"dottedLine","color":"#000","position":[7097,3422,7733,3657],"defaultText":""},"91096":{"kind":"ellipse","outlineOnly":true,"color":"#000","position":[7993,3445,8182,3634],"defaultText":""},"92096":{"kind":"dottedLine","color":"#000","position":[8266,3422,8902,3657],"defaultText":""},"93096":{"kind":"ellipse","outlineOnly":true,"color":"#000","position":[4485,4147,4674,4336],"defaultText":""},"94096":{"kind":"dottedLine","color":"#000","position":[4758,4124,5394,4359],"defaultText":""},"95096":{"kind":"ellipse","outlineOnly":true,"color":"#000","position":[5654,4147,5843,4336],"defaultText":""},"96096":{"kind":"dottedLine","color":"#000","position":[5927,4124,6563,4359],"defaultText":""},"97096":{"kind":"ellipse","outlineOnly":true,"color":"#000","position":[6824,4147,7013,4336],"defaultText":""},"98096":{"kind":"dottedLine","color":"#000","position":[7097,4124,7733,4359],"defaultText":""},"99096":{"kind":"ellipse","outlineOnly":true,"color":"#000","position":[7993,4147,8182,4336],"defaultText":""},"100096":{"kind":"dottedLine","color":"#000","position":[8266,4124,8902,4359],"defaultText":""},"101096":{"kind":"dottedLine","color":"#000","position":[4263,100,9050,4518],"defaultText":""},"102096":{"kind":"staticText","color":"#000","position":[4263,4618,5263,4868],"defaultText":"Comments:"},"103096":{"kind":"text","printable":true,"editable":true,"color":"#c0ffff","position":[4263,4868,9050,5468],"defaultText":""}}}
