{"copyright":"Copyright (c) 2001 DESI Telephone Labels, Inc.","group":"KS Telecom","typeCode":"KEY-28","description":"IDX 28","landscape":false,"width":5262,"height":5044,"origins":[[3478,2160]],"objects":{"5096":{"kind":"text","printable":true,"editable":true,"color":"#c0ffff","position":[100,350,5162,850],"defaultText":""},"6096":{"kind":"text","printable":true,"editable":true,"color":"#fff","position":[204,1374,1324,1699],"defaultText":"{\\rtf1\\ansi{\\fonttbl{\\f0\\ftnil Arial;}}{\\colortbl\\red0green0blue0;}\\f0\\cf0\\fs18\\b\\qc PROG}"},"7096":{"kind":"text","printable":true,"editable":true,"color":"#fff","position":[1450,1374,2570,1699],"defaultText":"{\\rtf1\\ansi{\\fonttbl{\\f0\\ftnil Arial;}}{\\colortbl\\red0green0blue0;}\\f0\\cf0\\fs18\\b\\qc CONF}"},"8096":{"kind":"text","printable":true,"editable":true,"color":"#fff","position":[2696,1374,3816,1699],"defaultText":"{\\rtf1\\ansi{\\fonttbl{\\f0\\ftnil Arial;}}{\\colortbl\\red0green0blue0;}\\f0\\cf0\\fs18\\b\\qc FLASH}"},"9096":{"kind":"text","printable":true,"editable":true,"color":"#fff","position":[3942,1374,5062,1699],"defaultText":"{\\rtf1\\ansi{\\fonttbl{\\f0\\ftnil Arial;}}{\\colortbl\\red0green0blue0;}\\f0\\cf0\\fs18\\b\\qc MSG}"},"10096":{"kind":"text","printable":true,"editable":true,"color":"#fff","position":[204,1995,1324,2320],"defaultText":"{\\rtf1\\ansi{\\fonttbl{\\f0\\ftnil Arial;}}{\\colortbl\\red0green0blue0;}\\f0\\cf0\\fs18\\b\\qc INT/SPEED}"},"11096":{"kind":"text","printable":true,"editable":true,"color":"#fff","position":[1450,1995,2570,2320],"defaultText":"{\\rtf1\\ansi{\\fonttbl{\\f0\\ftnil Arial;}}{\\colortbl\\red0green0blue0;}\\f0\\cf0\\fs18\\b\\qc DND/DATA}"},"12096":{"kind":"text","printable":true,"editable":true,"color":"#fff","position":[2696,1995,3816,2320],"defaultText":"{\\rtf1\\ansi{\\fonttbl{\\f0\\ftnil Arial;}}{\\colortbl\\red0green0blue0;}\\f0\\cf0\\fs18\\b\\qc CAMP}"},"13096":{"kind":"text","printable":true,"editable":true,"color":"#fff","position":[3942,1995,5062,2320],"defaultText":"{\\rtf1\\ansi{\\fonttbl{\\f0\\ftnil Arial;}}{\\colortbl\\red0green0blue0;}\\f0\\cf0\\fs18\\b\\qc MIC}"},"14096":{"kind":"text","printable":true,"editable":true,"color":"#fff","position":[204,2616,1324,2941],"defaultText":""},"15096":{"kind":"text","printable":true,"editable":true,"color":"#fff","position":[1450,2616,2570,2941],"defaultText":""},"16096":{"kind":"text","printable":true,"editable":true,"color":"#fff","position":[2696,2616,3816,2941],"defaultText":""},"17096":{"kind":"text","printable":true,"editable":true,"color":"#fff","position":[3942,2616,5062,2941],"defaultText":""},"18096":{"kind":"text","printable":true,"editable":true,"color":"#fff","position":[204,3237,1324,3562],"defaultText":""},"19096":{"kind":"text","printable":true,"editable":true,"color":"#fff","position":[1450,3237,2570,3562],"defaultText":""},"20096":{"kind":"text","printable":true,"editable":true,"color":"#fff","position":[2696,3237,3816,3562],"defaultText":""},"21096":{"kind":"text","printable":true,"editable":true,"color":"#fff","position":[3942,3237,5062,3562],"defaultText":""},"22096":{"kind":"text","printable":true,"editable":true,"color":"#fff","position":[204,3858,1324,4183],"defaultText":""},"23096":{"kind":"text","printable":true,"editable":true,"color":"#fff","position":[1450,3858,2570,4183],"defaultText":""},"24096":{"kind":"text","printable":true,"editable":true,"color":"#fff","position":[2696,3858,3816,4183],"defaultText":""},"25096":{"kind":"text","printable":true,"editable":true,"color":"#fff","position":[3942,3858,5062,4183],"defaultText":""},"26096":{"kind":"text","printable":true,"editable":true,"color":"#fff","position":[204,4507,1324,4832],"defaultText":""},"27096":{"kind":"text","printable":true,"editable":true,"color":"#fff","position":[1450,4507,2570,4832],"defaultText":""},"28096":{"kind":"text","printable":true,"editable":true,"color":"#fff","position":[2696,4507,3816,4832],"defaultText":""},"29096":{"kind":"text","printable":true,"editable":true,"color":"#fff","position":[3942,4507,5062,4832],"defaultText":""},"30096":{"kind":"dottedLine","color":"#000","position":[348,1119,1180,1333],"defaultText":""},"31096":{"kind":"dottedLine","color":"#000","position":[1592,1119,2424,1333],"defaultText":""},"32096":{"kind":"dottedLine","color":"#000","position":[2836,1119,3668,1333],"defaultText":""},"33096":{"kind":"dottedLine","color":"#000","position":[4080,1119,4912,1333],"defaultText":""},"34096":{"kind":"dottedLine","color":"#000","position":[348,1740,1180,1954],"defaultText":""},"35096":{"kind":"dottedLine","color":"#000","position":[1592,1740,2424,1954],"defaultText":""},"36096":{"kind":"dottedLine","color":"#000","position":[2836,1740,3668,1954],"defaultText":""},"37096":{"kind":"dottedLine","color":"#000","position":[4080,1740,4912,1954],"defaultText":""},"38096":{"kind":"dottedLine","color":"#000","position":[348,2361,1180,2575],"defaultText":""},"39096":{"kind":"dottedLine","color":"#000","position":[1592,2361,2424,2575],"defaultText":""},"40096":{"kind":"dottedLine","color":"#000","position":[2836,2361,3668,2575],"defaultText":""},"41096":{"kind":"dottedLine","color":"#000","position":[4080,2361,4912,2575],"defaultText":""},"42096":{"kind":"dottedLine","color":"#000","position":[348,2982,1180,3196],"defaultText":""},"43096":{"kind":"dottedLine","color":"#000","position":[1592,2982,2424,3196],"defaultText":""},"44096":{"kind":"dottedLine","color":"#000","position":[2836,2982,3668,3196],"defaultText":""},"45096":{"kind":"dottedLine","color":"#000","position":[4080,2982,4912,3196],"defaultText":""},"46096":{"kind":"dottedLine","color":"#000","position":[348,3603,1180,3817],"defaultText":""},"47096":{"kind":"dottedLine","color":"#000","position":[1592,3603,2424,3817],"defaultText":""},"48096":{"kind":"dottedLine","color":"#000","position":[2836,3603,3668,3817],"defaultText":""},"49096":{"kind":"dottedLine","color":"#000","position":[4080,3603,4912,3817],"defaultText":""},"50096":{"kind":"dottedLine","color":"#000","position":[348,4238,1180,4452],"defaultText":""},"51096":{"kind":"dottedLine","color":"#000","position":[1592,4238,2424,4452],"defaultText":""},"52096":{"kind":"dottedLine","color":"#000","position":[2836,4238,3668,4452],"defaultText":""},"53096":{"kind":"dottedLine","color":"#000","position":[4080,4238,4912,4452],"defaultText":""},"54096":{"kind":"dottedLine","color":"#000","position":[100,950,5162,4944],"defaultText":""},"55096":{"kind":"staticText","color":"#000","position":[100,100,1100,350],"defaultText":"Comments:"}}}
