{"copyright":"Copyright © 2003 DESI Telephone Labels, Inc.","group":"TeleMatrix 2000 Series","typeCode":"MAR2K1AT","description":"Phone Number Strips (One-At-A-Time)","landscape":false,"width":2315,"height":1525,"origins":[[1283,2730],[1283,3940],[1283,5150],[1283,6360],[1283,7570],[3758,2730],[3758,3940],[3758,5150],[3758,6360],[3758,7570],[6233,2730],[6233,3940],[6233,5150],[6233,6360],[6233,7570],[8708,2730],[8708,3940],[8708,5150],[8708,6360],[8708,7570]],"objects":{"5096":{"kind":"staticText","color":"#000","position":[100,100,1100,350],"defaultText":"Comments:"},"6096":{"kind":"text","printable":true,"editable":true,"color":"#c0ffff","position":[100,350,2215,650],"defaultText":""},"7096":{"kind":"text","printable":true,"editable":true,"color":"#fff","position":[100,750,2215,1425],"defaultText":""}}}
