{"copyright":"Copyright © 2004 DESI Telephone Labels, Inc.","group":"Ericsson Dialog 4200","typeCode":"ERI4422","description":"4422 IP Office","landscape":false,"width":2541,"height":4386,"origins":[[2973,2923],[6780,2923],[2973,7686],[6780,7686]],"objects":{"4496":{"kind":"staticText","color":"#000","position":[100,100,1100,350],"defaultText":"Comments:"},"4796":{"kind":"text","printable":true,"editable":true,"color":"#c0ffff","position":[100,350,2441,850],"defaultText":""},"5096":{"kind":"text","printable":true,"editable":true,"color":"#fff","position":[160,980,2381,1208],"defaultText":"{\\rtf1\\ansi{\\fonttbl{\\f0\\ftnil Arial;}}{\\colortbl;}\\f0\\cf0\\fs16\\b\\qc }"},"6096":{"kind":"text","printable":true,"editable":true,"color":"#fff","position":[160,1228,1255,1804],"defaultText":"{\\rtf1\\ansi{\\fonttbl{\\f0\\ftnil Arial;}}{\\colortbl;}\\f0\\cf0\\fs18\\b\\i\\ql Conference}"},"7096":{"kind":"text","printable":true,"editable":true,"color":"#fff","position":[1286,1228,2381,1804],"defaultText":"{\\rtf1\\ansi{\\fonttbl{\\f0\\ftnil Arial;}}{\\colortbl;}\\f0\\cf0\\fs18\\b\\i\\qr Settings}"},"8096":{"kind":"text","printable":true,"editable":true,"color":"#fff","position":[160,1847,1255,2423],"defaultText":"{\\rtf1\\ansi{\\fonttbl{\\f0\\ftnil Arial;}}{\\colortbl;}\\f0\\cf0\\fs18\\b\\i\\ql Transfer}"},"9096":{"kind":"text","printable":true,"editable":true,"color":"#fff","position":[1286,1847,2381,2423],"defaultText":"{\\rtf1\\ansi{\\fonttbl{\\f0\\ftnil Arial;}}{\\colortbl;}\\f0\\cf0\\fs18\\b\\i\\qr Follow-me}"},"10096":{"kind":"text","printable":true,"editable":true,"color":"#fff","position":[160,2466,1255,3042],"defaultText":"{\\rtf1\\ansi{\\fonttbl{\\f0\\ftnil Arial;}}{\\colortbl;}\\f0\\cf0\\fs18\\b\\i\\ql Inquiry}"},"11096":{"kind":"text","printable":true,"editable":true,"color":"#fff","position":[1286,2466,2381,3042],"defaultText":"{\\rtf1\\ansi{\\fonttbl{\\f0\\ftnil Arial;}}{\\colortbl;}\\f0\\cf0\\fs18\\b\\i\\qr Message}"},"12096":{"kind":"text","printable":true,"editable":true,"color":"#fff","position":[160,3085,1255,3661],"defaultText":"{\\rtf1\\ansi{\\fonttbl{\\f0\\ftnil Arial;}}{\\colortbl;}\\f0\\cf0\\fs18\\b\\i\\ql Line 2}"},"13096":{"kind":"text","printable":true,"editable":true,"color":"#fff","position":[1286,3085,2381,3661],"defaultText":"{\\rtf1\\ansi{\\fonttbl{\\f0\\ftnil Arial;}}{\\colortbl;}\\f0\\cf0\\fs18\\b\\i\\qr Free on 2nd}"},"14096":{"kind":"text","printable":true,"editable":true,"color":"#fff","position":[160,3704,1255,4256],"defaultText":"{\\rtf1\\ansi{\\fonttbl{\\f0\\ftnil Arial;}}{\\colortbl;}\\f0\\cf0\\fs18\\b\\i\\ql Line 1}"},"15096":{"kind":"text","printable":true,"editable":true,"color":"#fff","position":[1286,3704,2381,4256],"defaultText":"{\\rtf1\\ansi{\\fonttbl{\\f0\\ftnil Arial;}}{\\colortbl;}\\f0\\cf0\\fs18\\b\\i\\qr Call List}"},"16096":{"kind":"dottedLine","color":"#000","position":[100,950,2441,4286],"defaultText":""}}}
